Workbook

Sheet Xero -EmployeeUpload
A1: Title | B1: First Name | C1: Middle Name | D1: Last Name | E1: Date of Birth | F1: Gender | G1: Job Title | H1: Email | I1: Start Date | J1: Address Line 1 | K1: Address Line 2 | L1: Suburb | M1: State | N1: Postcode | O1: Phone Number | P1: Classification
A2: Ms | B2: Mei Lin | D2: Cheong | E2: 1990/12/31 | F2: Female | G2: CEO | I2: 2019/06/04 | J2: 33 West St | L2: Nedlands | M2: WA | N2: 6009 | O2: 0400941930 | P2: Award Free
A3: Ms | B3: Sophia | D3: Bennett | E3: 1995/10/12 | F3: Female | G3: Executive Assistant | I3: 2019/04/01 | J3: 30 Cable St | L3: Subiaco | M3: WA | N3: 6008 | O3: 0400108139 | P3: Clerks Award
A4: Mr | B4: Rajesh | D4: Patel | E4: 1993/03/30 | F4: Male | G4: Chief Financial Officer | I4: 2022/12/17 | J4: 28 Dwyer St | L4: Subiaco | M4: WA | N4: 6008 | O4: 0400962841 | P4: Clerks Award
A5: Mr | B5: Ethan | D5: Brooks | E5: 1993/03/09 | F5: Male | G5: Accounts Receivable | I5: 2020/03/25 | J5: 1 Brigid St | L5: Crawley | M5: WA | N5: 6009 | O5: 0400270026 | P5: Clerks Award
A6: Mr | B6: Liam | D6: Parker | E6: 1991/03/02 | F6: Male | G6: Accounts Payable | I6: 2022/09/19 | J6: 89 Foam St | L6: Daglish | M6: WA | N6: 6008 | O6: 0400925891 | P6: Clerks Award
A7: Mr | B7: Fred | D7: Payrits | E7: 1972/02/28 | F7: Male | G7: Payroll Officer | I7: 2021/11/14 | J7: 46 Russell St | L7: Innaloo | M7: WA | N7: 6018 | O7: 0400677756 | P7: Clerks Award
A8: Mr | B8: Lucas | D8: Reed | E8: 1976/04/11 | F8: Male | G8: Sales Manager | I8: 2018/01/26 | J8: 75 Maple St | L8: Leederville | M8: WA | N8: 6007 | O8: 0400891766 | P8: General Retail Award
A9: Mr | B9: Henry | D9: Davis | E9: 1973/09/15 | F9: Male | G9: Sales Team Leader | I9: 2022/10/01 | J9: 13 Green St | L9: Morley | M9: WA | N9: 6062 | O9: 0400932160 | P9: General Retail Award
A10: Mr | B10: Noah | D10: Turner | E10: 1979/02/25 | F10: Male | G10: Sales Team Leader | I10: 2021/07/18 | J10: 78 Elm St | L10: Leederville | M10: WA | N10: 6007 | O10: 0400659788 | P10: General Retail Award
A11: Ms | B11: Chantel | D11: Dubois | E11: 1982/07/27 | F11: Female | G11: Sales Rep | I11: 2020/07/26 | J11: 75 Ship St | L11: Bayswater | M11: WA | N11: 6053 | O11: 0400748241 | P11: General Retail Award
A12: Mrs | B12: Ella | D12: Morgan | E12: 1983/10/11 | F12: Female | G12: Sales Rep | I12: 2022/06/15 | J12: 64 Viper St | L12: West Perth | M12: WA | N12: 6005 | O12: 0400342606 | P12: General Retail Award
A13: Mr | B13: Matteo | D13: Bianchi | E13: 1970/11/19 | F13: Male | G13: Sales Rep | I13: 2019/05/28 | J13: 24 Finch St | L13: Joondalup | M13: WA | N13: 6027 | O13: 0400531042 | P13: General Retail Award
... A21: Mx | B21: Emily | D21: Scott | E21: 1993/12/03 | F21: Female | G21: Operations Staff | I21: 2018/07/28 | J21: 79 Player St | L21: Wanneroo | M21: WA | N21: 6065 | O21: 0400706959 | P21: Manufacturing Award

Sheet Employee Master
A1: Employee ID | B1: First Name | C1: Family Name | D1: Full Name | E1: Date of Birth | F1: Gender | G1: Contact Details | H1: Address | I1: Suburb | J1: PostCode | K1: Emergency Contact | L1: Employment Status | M1: Hire Date | N1: Termination Date | O1: Job Title | P1: Department | Q1: Office Location | R1: Region/State | S1: Country | T1: Manager | U1: Award/Agreement | V1: Employment Type
A2: E001 | B2: Mei Lin | C2: Cheong | D2: Cheong Mei Lin | E2: 33238 | F2: Female | G2: 0400941930 | H2: 33 West St | I2: Nedlands | J2: 6009 | L2: Active | M2: 43620 | O2: CEO | P2: Executive | Q2: Subiaco Office | R2: WA | S2: Australia | T2: Manager TBD | U2: Award Free | V2: Full-time
A3: E002 | B3: Sophia | C3: Bennett | D3: Sophia Bennett | E3: 34984 | F3: Female | G3: 0400108139 | H3: 30 Cable St | I3: Subiaco | J3: 6008 | L3: Active | M3: 43556 | O3: Executive Assistant | P3: Executive | Q3: Subiaco Office | R3: WA | S3: Australia | T3: Manager TBD | U3: Clerks Award | V3: Full-time
A4: E003 | B4: Rajesh | C4: Patel | D4: Rajesh Patel | E4: 34058 | F4: Male | G4: 0400962841 | H4: 28 Dwyer St | I4: Subiaco | J4: 6008 | L4: Active | M4: 44912 | O4: Chief Financial Officer | P4: Finance | Q4: Subiaco Office | R4: WA | S4: Australia | T4: Manager TBD | U4: Clerks Award | V4: Full-time
A5: E004 | B5: Ethan | C5: Brooks | D5: Ethan Brooks | E5: 34037 | F5: Male | G5: 0400270026 | H5: 1 Brigid St | I5: Crawley | J5: 6009 | L5: Active | M5: 43915 | O5: Accounts Receivable | P5: Finance | Q5: Subiaco Office | R5: WA | S5: Australia | T5: Manager TBD | U5: Clerks Award | V5: Full-time
A6: E005 | B6: Liam | C6: Parker | D6: Liam Parker | E6: 33299 | F6: Male | G6: 0400925891 | H6: 89 Foam St | I6: Daglish | J6: 6008 | L6: Active | M6: 44823 | O6: Accounts Payable | P6: Finance | Q6: Subiaco Office | R6: WA | S6: Australia | T6: Manager TBD | U6: Clerks Award | V6: Full-time
A7: E006 | B7: Fred | C7: Payrits | D7: Fred Payrits | E7: 26357 | F7: Male | G7: 0400677756 | H7: 46 Russell St | I7: Innaloo | J7: 6018 | L7: Active | M7: 44514 | O7: Payroll Officer | P7: Finance | Q7: Subiaco Office | R7: WA | S7: Australia | T7: Manager TBD | U7: Clerks Award | V7: Full-time
A8: E007 | B8: Lucas | C8: Reed | D8: Lucas Reed | E8: 27861 | F8: Male | G8: 0400891766 | H8: 75 Maple St | I8: Leederville | J8: 6007 | L8: Active | M8: 43126 | O8: Sales Manager | P8: Sales | Q8: Subiaco Office | R8: WA | S8: Australia | T8: Manager TBD | U8: General Retail Award | V8: Full-time
A9: E008 | B9: Henry | C9: Davis | D9: Henry Davis | E9: 26922 | F9: Male | G9: 0400932160 | H9: 13 Green St | I9: Morley | J9: 6062 | L9: Active | M9: 44835 | O9: Sales Team Leader | P9: Sales | Q9: Joondalup | R9: WA | S9: Australia | T9: Manager TBD | U9: General Retail Award | V9: Full-time
A10: E009 | B10: Noah | C10: Turner | D10: Noah Turner | E10: 28911 | F10: Male | G10: 0400659788 | H10: 78 Elm St | I10: Leederville | J10: 6007 | L10: Active | M10: 44395 | O10: Sales Team Leader | P10: Sales | Q10: Subiaco Office | R10: WA | S10: Australia | T10: Manager TBD | U10: General Retail Award | V10: Full-time
A11: E010 | B11: Chantel | C11: Dubois | D11: Chantel Dubois | E11: 30159 | F11: Female | G11: 0400748241 | H11: 75 Ship St | I11: Bayswater | J11: 6053 | L11: Active | M11: 44038 | O11: Sales Rep | P11: Sales | Q11: Joondalup | R11: WA | S11: Australia | T11: Manager TBD | U11: General Retail Award | V11: Full-time
A12: E011 | B12: Ella | C12: Morgan | D12: Ella Morgan | E12: 30600 | F12: Female | G12: 0400342606 | H12: 64 Viper St | I12: West Perth | J12: 6005 | L12: Active | M12: 44727 | O12: Sales Rep | P12: Sales | Q12: Subiaco Office | R12: WA | S12: Australia | T12: Manager TBD | U12: General Retail Award | V12: Full-time
A13: E012 | B13: Matteo | C13: Bianchi | D13: Matteo Bianchi | E13: 25891 | F13: Male | G13: 0400531042 | H13: 24 Finch St | I13: Joondalup | J13: 6027 | L13: Active | M13: 43613 | O13: Sales Rep | P13: Sales | Q13: Joondalup | R13: WA | S13: Australia | T13: Manager TBD | U13: General Retail Award | V13: Full-time
... A21: E020 | B21: Emily | C21: Scott | D21: Emily Scott | E21: 34306 | F21: Female | G21: 0400706959 | H21: 79 Player St | I21: Wanneroo | J21: 6065 | L21: Active | M21: 43309 | O21: Operations Staff | P21: Operations | Q21: Joondalup | R21: WA | S21: Australia | T21: Manager TBD | U21: Manufacturing Award | V21: Full-time

Sheet Leave Tracker
A1: Employee ID | B1: Leave Type | C1: Leave Balance (Days) | D1: Days Requested | E1: Days Approved | F1: Leave Taken Start | G1: Leave Taken End | H1: Leave Accrual Rate | I1: Notes
A2: E001 | B2: Annual Leave | C2: 100 | H2: 1.5 days/month
A3: E002 | B3: Annual Leave | C3: 45 | H3: 1.5 days/month
A4: E003 | B4: Annual Leave | C4: 76 | H4: 1.5 days/month
A5: E004 | B5: Annual Leave | C5: 1 | H5: 1.5 days/month
A6: E005 | B6: Annual Leave | C6: 5 | H6: 1.5 days/month
A7: E006 | B7: Annual Leave | C7: 4 | H7: 1.5 days/month
A8: E007 | B8: Annual Leave | C8: 0 | H8: 1.5 days/month
A9: E008 | B9: Annual Leave | C9: 36 | H9: 1.5 days/month
A10: E009 | B10: Annual Leave | C10: 51 | H10: 1.5 days/month
A11: E010 | B11: Annual Leave | C11: 19 | H11: 1.5 days/month
A12: E011 | B12: Annual Leave | C12: 18 | H12: 1.5 days/month
A13: E012 | B13: Annual Leave | C13: 22 | H13: 1.5 days/month
... A21: E020 | B21: Annual Leave | C21: 2 | H21: 1.5 days/month

Sheet Remuneration
A1: Employee ID | B1: Base Salary | C1: Award/Classification Level | D1: Allowances | E1: Commission | F1: Commission % | G1: Commision Earned | H1: Overtime Rate | I1: Superannuation % | J1: Bonus Eligibility | K1: Pay Cycle | L1: Salary | M1: Commission $ | N1: Total Package Value
A2: E001 | B2: 161780 | D2: 15000 | I2: 20 | J2: Yes | K2: Monthly | L2: 166780 | N2: =L2*(I2/100)+D2+L2+M2 -> 215136
A3: E002 | B3: 74149 | C3: 1 | H3: 1.5x | I3: 12 | J3: No | K3: Monthly | L3: 79149 | N3: =L3*(I3/100)+D3+L3+M3 -> 88646.88
A4: E003 | B4: 89628 | D4: 5000 | I4: 15 | J4: Yes | K4: Monthly | L4: 134628 | N4: =L4*(I4/100)+D4+L4+M4 -> 159822.2
A5: E004 | B5: 141787 | C5: 5 | H5: 1.5x | I5: 12 | J5: No | K5: Monthly | L5: 64678 | N5: =L5*(I5/100)+D5+L5+M5 -> 72439.36
A6: E005 | B6: 131471 | C6: 5 | H6: 1.5x | I6: 12 | J6: No | K6: Monthly | L6: 63647 | N6: =L6*(I6/100)+D6+L6+M6 -> 71284.64
A7: E006 | B7: 95024 | C7: 5 | H7: 1.5x | I7: 12 | J7: No | K7: Monthly | L7: 60024 | N7: =L7*(I7/100)+D7+L7+M7 -> 67226.88
A8: E007 | B8: 163774 | D8: 5000 | E8: Yes | F8: 0.15 | G8: =AVERAGE(G9:G10) -> 0.78333333 | I8: 15 | J8: No | K8: Monthly | L8: 168774 | M8: =F8*L8/12*G8 -> 1652.5787 | N8: =L8*(I8/100)+D8+L8+M8 -> 200742.68
A9: E008 | B9: 121433 | C9: 3 | D9: 300 | E9: Yes | F9: 0.1 | G9: =AVERAGE(G11:G13) -> 0.81666667 | H9: 1.5x | I9: 12 | J9: No | K9: Monthly | L9: 126433 | M9: =F9*L9/12*G9 -> 860.44681 | N9: =L9*(I9/100)+D9+L9+M9 -> 142765.41
A10: E009 | B10: 123921 | C10: 3 | D10: 300 | E10: Yes | F10: 0.1 | G10: =AVERAGE(G14:G16) -> 0.75 | H10: 1.5x | I10: 12 | J10: No | K10: Monthly | L10: 128921 | M10: =F10*L10/12*G10 -> 805.75625 | N10: =L10*(I10/100)+D10+L10+M10 -> 145497.28
A11: E010 | B11: 87870 | C11: 3 | D11: 300 | E11: Yes | F11: 0.1 | G11: 0.65 | H11: 1.5x | I11: 12 | J11: No | K11: Monthly | L11: 92870 | M11: =F11*L11/12*G11 -> 503.04583 | N11: =L11*(I11/100)+D11+L11+M11 -> 104817.45
A12: E011 | B12: 114495 | C12: 3 | D12: 300 | E12: Yes | F12: 0.1 | G12: 1 | H12: 1.5x | I12: 12 | J12: No | K12: Monthly | L12: 92495 | M12: =F12*L12/12*G12 -> 770.79167 | N12: =L12*(I12/100)+D12+L12+M12 -> 104665.19
A13: E012 | B13: 78819 | C13: 3 | D13: 300 | E13: Yes | F13: 0.1 | G13: 0.8 | H13: 1.5x | I13: 12 | J13: No | K13: Monthly | L13: 63819 | M13: =F13*L13/12*G13 -> 425.46 | N13: =L13*(I13/100)+D13+L13+M13 -> 72202.74
A14: E013 | B14: 107039 | C14: 3 | D14: 300 | E14: Yes | F14: 0.1 | G14: 0.75 | H14: 1.5x | I14: 12 | J14: No | K14: Monthly | L14: 62039 | M14: =F14*L14/12*G14 -> 387.74375 | N14: =L14*(I14/100)+D14+L14+M14 -> 70171.424
A15: E014 | B15: 60198 | C15: 3 | D15: 300 | E15: Yes | F15: 0.1 | G15: 1 | H15: 1.5x | I15: 12 | J15: No | K15: Monthly | L15: 65198 | M15: =F15*L15/12*G15 -> 543.31667 | N15: =L15*(I15/100)+D15+L15+M15 -> 73865.077
A16: E015 | B16: 153999 | C16: 3 | D16: 300 | E16: Yes | F16: 0.1 | G16: 0.5 | H16: 1.5x | I16: 12 | J16: No | K16: Monthly | L16: 65999 | M16: =F16*L16/12*G16 -> 274.99583 | N16: =L16*(I16/100)+D16+L16+M16 -> 74493.876
A17: E016 | B17: 128339 | D17: 5000 | I17: 15 | J17: Yes | K17: Monthly | L17: 133339 | N17: =L17*(I17/100)+D17+L17+M17 -> 158339.85
A18: E017 | B18: 104608 | C18: 5 | H18: 1.5x | I18: 12 | J18: No | K18: Monthly | L18: 79608 | N18: =L18*(I18/100)+D18+L18+M18 -> 89160.96
A19: E018 | B19: 88902 | C19: 5 | H19: 1.5x | I19: 12 | J19: No | K19: Monthly | L19: 73902 | N19: =L19*(I19/100)+D19+L19+M19 -> 82770.24
A20: E019 | B20: 177257 | C20: 5 | H20: 1.5x | I20: 12 | J20: No | K20: Monthly | L20: 82257 | N20: =L20*(I20/100)+D20+L20+M20 -> 92127.84
A21: E020 | B21: 151434 | C21: 5 | H21: 1.5x | I21: 12 | J21: No | K21: Monthly | L21: 56434 | N21: =L21*(I21/100)+D21+L21+M21 -> 63206.08

Sheet Position Details
A1: Employee ID | B1: Position Title | C1: Position Level | D1: Skills Required | E1: Qualifications | F1: Qualification Date | G1: Expiry Date | H1: Licenses/Permits | I1: Competency Status
A2: E001 | B2: CEO | C2: M3 | F2: 43691 | G2: 46137 | H2: Driver License
A3: E002 | B3: Executive Assistant | C3: C1 | F3: 46017 | H3: MS 365 Suite
A4: E003 | B4: Chief Financial Officer | C4: M1 | F4: 42633 | G4: 46145 | H4: Driver License
A5: E004 | B5: Accounts Receivable | C5: F2 | F5: 44709 | H5: Xero
A6: E005 | B6: Accounts Payable | C6: F2 | F6: 43143 | H6: Reckon
A7: E006 | B7: Payroll Officer | C7: F2 | E7: Cert IV HR | F7: 45683 | H7: Bamboo
A8: E007 | B8: Sales Manager | C8: M1 | F8: 43721 | G8: 46274 | H8: Driver License
A9: E008 | B9: Sales Team Leader | C9: S5 | F9: 43601 | G9: 46227 | H9: Driver License
A10: E009 | B10: Sales Team Leader | C10: S5 | F10: 44142 | G10: 46171 | H10: Driver License
A11: E010 | B11: Sales Rep | C11: S1 | F11: 43376 | G11: 46161 | H11: Driver License
A12: E011 | B12: Sales Rep | C12: S3 | F12: 44029 | G12: 46288 | H12: Driver License
A13: E012 | B13: Sales Rep | C13: S3 | F13: 43592 | G13: 46114 | H13: Driver License
A14: E013 | B14: Sales Rep | C14: S3 | F14: 42473 | G14: 46189 | H14: Driver License
A15: E014 | B15: Sales Rep | C15: S1 | F15: 42318 | G15: 46090 | H15: Driver License
A16: E015 | B16: Sales Rep | C16: S1 | F16: 42551 | G16: 46013 | H16: Driver License
A17: E016 | B17: Operations Manager | C17: M1 | E17: Cert III HR | F17: 42837 | H17: ERP
A18: E017 | B18: Operations Staff | C18: O1 | F18: 43912 | G18: 46143 | H18: Driver License - Truck
A19: E018 | B19: Operations Staff | C19: O1 | F19: 43423 | G19: 46214 | H19: Forklift
A20: E019 | B20: Operations Staff | C20: O3 | F20: 44020 | G20: 46095 | H20: Forklift
A21: E020 | B21: Operations Staff | C21: O1 | F21: 43022 | G21: 46103 | H21: Forklift

Sheet Organisation Structure
A1: Employee ID | B1: Position Title | C1: Position Level | D1: Manager ID | E1: Manager Name | F1: Department / Function | G1: Office Location | H1: Region/State | I1: Country | J1: Date Appointed | K1: Time in Role (YY/MM) | L1: Direct Reports
A2: E001 | B2: CEO | C2: M3 | F2: Executive | G2: Subiaco Office | H2: WA | I2: Australia | J2: 43620 | K2: =NOW()-J2 -> 2365.7166 | L2: 4
A3: E002 | B3: Executive Assistant | C3: C1 | D3: E001 | E3: Mei Lin Cheong | F3: Executive | G3: Subiaco Office | H3: WA | I3: Australia | J3: 43556 | K3: =NOW()-J3 -> 2429.7166 | L3: 0
A4: E003 | B4: Chief Financial Officer | C4: M1 | D4: E001 | E4: Mei Lin Cheong | F4: Finance | G4: Subiaco Office | H4: WA | I4: Australia | J4: 44912 | K4: =NOW()-J4 -> 1073.7166 | L4: 3
A5: E004 | B5: Accounts Receivable | C5: F2 | D5: E003 | E5: Rajesh Patel | F5: Finance | G5: Subiaco Office | H5: WA | I5: Australia | J5: 43915 | K5: =NOW()-J5 -> 2070.7166 | L5: 1
A6: E005 | B6: Accounts Payable | C6: F2 | D6: E003 | E6: Rajesh Patel | F6: Finance | G6: Subiaco Office | H6: WA | I6: Australia | J6: 44823 | K6: =NOW()-J6 -> 1162.7166 | L6: 0
A7: E006 | B7: Payroll Officer | C7: F2 | D7: E003 | E7: Rajesh Patel | F7: Finance | G7: Subiaco Office | H7: WA | I7: Australia | J7: 44514 | K7: =NOW()-J7 -> 1471.7166 | L7: 0
A8: E007 | B8: Sales Manager | C8: M1 | D8: E001 | E8: Mei Lin Cheong | F8: Sales | G8: Subiaco Office | H8: WA | I8: Australia | J8: 43126 | K8: =NOW()-J8 -> 2859.7166 | L8: 4
A9: E008 | B9: Sales Team Leader | C9: S5 | D9: E007 | E9: Lucas Reed | F9: Sales | G9: Joondalup Office | H9: WA | I9: Australia | J9: 44835 | K9: =NOW()-J9 -> 1150.7166 | L9: 5
A10: E009 | B10: Sales Team Leader | C10: S5 | D10: E007 | E10: Lucas Reed | F10: Sales | G10: Subiaco Office | H10: WA | I10: Australia | J10: 44395 | K10: =NOW()-J10 -> 1590.7166 | L10: 3
A11: E010 | B11: Sales Rep | C11: S1 | D11: E008 | E11: Henry Davis | F11: Sales | G11: Joondalup Office | H11: WA | I11: Australia | J11: 44038 | K11: =NOW()-J11 -> 1947.7166 | L11: 2
A12: E011 | B12: Sales Rep | C12: S3 | D12: E008 | E12: Henry Davis | F12: Sales | G12: Joondalup Office | H12: WA | I12: Australia | J12: 44727 | K12: =NOW()-J12 -> 1258.7166 | L12: 3
A13: E012 | B13: Sales Rep | C13: S3 | D13: E008 | E13: Henry Davis | F13: Sales | G13: Joondalup Office | H13: WA | I13: Australia | J13: 43613 | K13: =NOW()-J13 -> 2372.7166 | L13: 4
A14: E013 | B14: Sales Rep | C14: S3 | D14: E009 | E14: Noah Turner | F14: Sales | G14: Subiaco Office | H14: WA | I14: Australia | J14: 44175 | K14: =NOW()-J14 -> 1810.7166 | L14: 1
... A21: E020 | B21: Operations Staff | C21: O1 | D21: E016 | E21: Thomas Murray | F21: Operations | G21: Joondalup Office | H21: WA | I21: Australia | J21: 43309 | K21: =NOW()-J21 -> 2676.7166 | L21: 4

Sheet Performance
A1: Employee ID | B1: Review Date | C1: Performance Rating | D1: Potential Rating | E1: Time in Role | F1: Goals/Objectives | G1: Achievement Status | H1: Development Plan Status | I1: Last Promotion Date | J1: Next Review Date
A2: E001 | B2: 45636 | C2: 5 | D2: Medium | E2: ='Organisation Structure'!K2 -> 2365.7166 | F2: NPS | G2: 98% | H2: Active | I2: 43620 | J2: 46002
A3: E002 | B3: 45636 | C3: 2 | D3: Medium | E3: ='Organisation Structure'!K3 -> 2429.7166 | G3: 79% | H3: Active | I3: 43556 | J3: 46002
A4: E003 | B4: 45636 | C4: 5 | D4: Medium | E4: ='Organisation Structure'!K4 -> 1073.7166 | G4: 86% | H4: Active | I4: 44912 | J4: 46002
A5: E004 | B5: 45636 | C5: 3 | D5: High | E5: ='Organisation Structure'!K5 -> 2070.7166 | G5: 92% | H5: Active | I5: 43915 | J5: 46002
A6: E005 | B6: 45636 | C6: 2 | D6: High | E6: ='Organisation Structure'!K6 -> 1162.7166 | G6: 100% | H6: Active | I6: 44823 | J6: 46002
A7: E006 | B7: 45636 | C7: 5 | D7: Low | E7: ='Organisation Structure'!K7 -> 1471.7166 | G7: 58% | H7: Active | I7: 44514 | J7: 46002
A8: E007 | B8: 45636 | C8: 2 | D8: High | E8: ='Organisation Structure'!K8 -> 2859.7166 | F8: Sales Growth | G8: 76% | H8: Active | I8: 43126 | J8: 46002
A9: E008 | B9: 45636 | C9: 2 | D9: Low | E9: ='Organisation Structure'!K9 -> 1150.7166 | F9: Sales Growth | G9: 75% | H9: Active | I9: 44835 | J9: 46002
A10: E009 | B10: 45636 | C10: 2 | D10: Low | E10: ='Organisation Structure'!K10 -> 1590.7166 | F10: Sales Growth | G10: 52% | H10: Active | I10: 44395 | J10: 46002
A11: E010 | B11: 45636 | C11: 5 | D11: Low | E11: ='Organisation Structure'!K11 -> 1947.7166 | F11: Sales Growth | G11: 61% | H11: Active | I11: 44038 | J11: 46002
A12: E011 | B12: 45636 | C12: 5 | D12: Low | E12: ='Organisation Structure'!K12 -> 1258.7166 | F12: Sales Growth | G12: 92% | H12: Active | I12: 44727 | J12: 46002
A13: E012 | B13: 45636 | C13: 5 | D13: Medium | E13: ='Organisation Structure'!K13 -> 2372.7166 | F13: Sales Growth | G13: 75% | H13: Active | I13: 43613 | J13: 46002
A14: E013 | B14: 45636 | C14: 2 | D14: Low | E14: ='Organisation Structure'!K14 -> 1810.7166 | F14: Sales Growth | G14: 84% | H14: Active | I14: 44175 | J14: 46002
A15: E014 | B15: 45636 | C15: 1 | D15: Medium | E15: ='Organisation Structure'!K15 -> 2742.7166 | F15: Sales Growth | G15: 56% | H15: Active | I15: 43243 | J15: 46002
A16: E015 | B16: 45636 | C16: 1 | D16: High | E16: ='Organisation Structure'!K16 -> 1872.7166 | F16: Sales Growth | G16: 91% | H16: Active | I16: 44113 | J16: 46002
A17: E016 | B17: 45636 | C17: 3 | D17: Low | E17: ='Organisation Structure'!K17 -> 2177.7166 | G17: 58% | H17: Active | I17: 43808 | J17: 46002
A18: E017 | B18: 45636 | C18: 5 | D18: High | E18: ='Organisation Structure'!K18 -> 2334.7166 | G18: 74% | H18: Active | I18: 43651 | J18: 46002
A19: E018 | B19: 45636 | C19: 5 | D19: Low | E19: ='Organisation Structure'!K19 -> 1645.7166 | G19: 52% | H19: Active | I19: 44340 | J19: 46002
A20: E019 | B20: 45636 | C20: 4 | D20: High | E20: ='Organisation Structure'!K20 -> 2634.7166 | G20: 96% | H20: Active | I20: 43351 | J20: 46002
A21: E020 | B21: 45636 | C21: 5 | D21: Low | E21: ='Organisation Structure'!K21 -> 2676.7166 | G21: 94% | H21: Active | I21: 43309 | J21: 46002

Sheet Succession Planning
A1: Employee ID | B1: Current Position | C1: Performance Rating | D1: Potential Rating | E1: Future Roles | F1: Ready Now Roles | G1: Ready 1-2 Yrs | H1: Likely Backfill Candidate | I1: Development Needs | J1: Target Readiness Date
A2: E001 | B2: CEO | C2: =Performance!C2 -> 5 | D2: Medium | F2: No | H2: E003 | I2: Leadership Training | J2: 46024
A3: E002 | B3: Executive Assistant | C3: =Performance!C3 -> 2 | D3: Medium | F3: No | J3: 46031
A4: E003 | B4: Chief Financial Officer | C4: =Performance!C4 -> 5 | D4: Medium | E4: CEO | F4: Yes | H4: E007 | I4: Leadership Training | J4: 46073
A5: E004 | B5: Accounts Receivable | C5: =Performance!C5 -> 3 | D5: Medium | E5: CFO | F5: No | G5: Yes | J5: 46330
A6: E005 | B6: Accounts Payable | C6: =Performance!C6 -> 2 | D6: Medium | F6: No | J6: 46078
A7: E006 | B7: Payroll Officer | C7: =Performance!C7 -> 5 | D7: Medium | E7: HRO | F7: No | G7: Yes | J7: 46213
A8: E007 | B8: Sales Manager | C8: =Performance!C8 -> 2 | D8: Medium | E8: CFO | F8: Yes | H8: E008 | I8: Leadership Training | J8: 46040
A9: E008 | B9: Sales Team Leader | C9: =Performance!C9 -> 2 | D9: Medium | E9: Sales Manager | F9: No | G9: Yes | H9: E012 | I9: Leadership Training | J9: 46282
A10: E009 | B10: Sales Team Leader | C10: =Performance!C10 -> 2 | D10: Medium | F10: No | H10: E013 | I10: Leadership Training | J10: 46226
A11: E010 | B11: Sales Rep | C11: =Performance!C11 -> 5 | D11: Medium | F11: No | J11: 46175
A12: E011 | B12: Sales Rep | C12: =Performance!C12 -> 5 | D12: Medium | F12: No | J12: 46291
A13: E012 | B13: Sales Rep | C13: =Performance!C13 -> 5 | D13: Medium | E13: Sales Team Leader | F13: Yes | H13: E020 | J13: 46210
A14: E013 | B14: Sales Rep | C14: =Performance!C14 -> 2 | D14: Medium | E14: Sales Team Leader | F14: Yes | J14: 46228
A15: E014 | B15: Sales Rep | C15: =Performance!C15 -> 1 | D15: Medium | E15: Sales Team Leader | F15: Yes | J15: 46308
A16: E015 | B16: Sales Rep | C16: =Performance!C16 -> 1 | D16: Medium | E16: Sales Team Leader | F16: Yes | J16: 46268
A17: E016 | B17: Operations Manager | C17: =Performance!C17 -> 3 | D17: Medium | E17: CEO | F17: No | G17: No | H17: E017 | J17: 46137
A18: E017 | B18: Operations Staff | C18: =Performance!C18 -> 5 | D18: Medium | E18: Operations Manager | F18: Yes | J18: 46317
A19: E018 | B19: Operations Staff | C19: =Performance!C19 -> 5 | D19: Medium | E19: Operations Manager | F19: No | G19: Yes | J19: 46112
A20: E019 | B20: Operations Staff | C20: =Performance!C20 -> 4 | D20: Medium | E20: Manager | F20: No | G20: No | J20: 46095
A21: E020 | B21: Operations Staff | C21: =Performance!C21 -> 5 | D21: Medium | E21: Sales Rep | F21: Yes | J21: 46279

Sheet Engagement & Retention
A1: Employee ID | B1: Engagement Score | C1: Turnover Risk Score | D1: Absenteeism Rate | E1: Regrettable Loss Indicator | F1: Termination Reason
A2: E001 | B2: 89 | C2: High | D2: 7% | E2: Yes
A3: E002 | B3: 92 | C3: Low | D3: 4% | E3: Yes
A4: E003 | B4: 85 | C4: Medium | D4: 5% | E4: Yes
A5: E004 | B5: 59 | C5: High | D5: 2% | E5: No
A6: E005 | B6: 82 | C6: Low | D6: 2% | E6: Yes
A7: E006 | B7: 90 | C7: High | D7: 8% | E7: No
A8: E007 | B8: 65 | C8: High | D8: 5% | E8: Yes
A9: E008 | B9: 69 | C9: High | D9: 10% | E9: No
A10: E009 | B10: 98 | C10: High | D10: 7% | E10: No
A11: E010 | B11: 67 | C11: Low | D11: 6% | E11: Yes
A12: E011 | B12: 94 | C12: Medium | D12: 5% | E12: No
A13: E012 | B13: 54 | C13: High | D13: 5% | E13: No
... A21: E020 | B21: 62 | C21: Medium | D21: 7% | E21: No

Sheet Risk & Compliance
A1: Employee ID | B1: Compliance Training Completion % | C1: WHS Incident Involvement | D1: Incident Type | E1: Date | F1: Severity | G1: Time Lost | H1: Near Miss Count | I1: Injury Type | J1: Lost Time Injury Indicator | K1: Policy Breach Flag
A2: E001 | B2: 98 | C2: 1 | D2: None | H2: 0 | J2: No | K2: No
A3: E002 | B3: 91 | C3: 0 | D3: None | H3: 0 | J3: No | K3: No
A4: E003 | B4: 80 | C4: 1 | D4: None | H4: 0 | J4: No | K4: No
A5: E004 | B5: 84 | C5: 1 | D5: None | H5: 1 | J5: No | K5: No
A6: E005 | B6: 85 | C6: 2 | D6: None | H6: 1 | J6: No | K6: No
A7: E006 | B7: 96 | C7: 2 | D7: None | H7: 1 | J7: No | K7: No
A8: E007 | B8: 88 | C8: 0 | D8: None | H8: 1 | J8: No | K8: No
A9: E008 | B9: 85 | C9: 1 | D9: None | H9: 1 | J9: No | K9: No
A10: E009 | B10: 96 | C10: 1 | D10: None | H10: 1 | J10: No | K10: No
A11: E010 | B11: 96 | C11: 0 | D11: None | H11: 1 | J11: No | K11: No
A12: E011 | B12: 99 | C12: 1 | D12: None | H12: 0 | J12: No | K12: No
A13: E012 | B13: 81 | C13: 1 | D13: None | H13: 1 | J13: No | K13: No
... A21: E020 | B21: 83 | C21: 1 | D21: None | H21: 0 | J21: No | K21: No

Sheet Diversity & Inclusion
A1: Employee ID | B1: Gender | C1: Age Group | D1: Aboriginal/Torres Strait Islander Status | E1: CALD Background | F1: Disability Status | G1: LGBTQ+ Indicator | H1: Veteran Status | I1: Flexible Work Arrangement
A2: E001 | B2: Female | C2: 51+ | D2: No | E2: Yes | F2: Yes | G2: Yes | H2: No | I2: No
A3: E002 | B3: Female | C3: 31-40 | D3: Yes | E3: Yes | F3: No | G3: No | H3: Yes | I3: Yes
A4: E003 | B4: Male | C4: 31-40 | D4: No | E4: Yes | F4: No | G4: No | H4: No | I4: No
A5: E004 | B5: Male | C5: 41-50 | D5: No | E5: No | F5: No | G5: No | H5: No | I5: No
A6: E005 | B6: Male | C6: 41-50 | D6: No | E6: No | F6: Yes | G6: No | H6: No | I6: No
A7: E006 | B7: Male | C7: 41-50 | D7: No | E7: No | F7: No | G7: No | H7: Yes | I7: Yes
A8: E007 | B8: Male | C8: 31-40 | D8: No | E8: No | F8: No | G8: No | H8: No | I8: No
A9: E008 | B9: Male | C9: 31-40 | D9: No | E9: No | F9: No | G9: No | H9: No | I9: No
A10: E009 | B10: Male | C10: 20-30 | D10: No | E10: No | F10: No | G10: No | H10: No | I10: No
A11: E010 | B11: Female | C11: 41-50 | D11: No | E11: Yes | F11: No | G11: No | H11: No | I11: No
A12: E011 | B12: Female | C12: 51+ | D12: No | E12: No | F12: Yes | G12: No | H12: No | I12: No
... A21: E020 | B21: Female | C21: 41-50 | D21: No | E21: No | F21: No | G21: No | H21: Yes | I21: No

Sheet Recruitment
A1: Vacancy ID | B1: Employee ID | C1: Position Title | D1: Hiring ManagerID | E1: Source of Candidate | F1: Time to Fill | G1: Number of Vacancies | H1: Candidate Pipeline Stage | I1: Assessment Results | J1: Office Location | K1: Region/State | L1: Country
A2: V001 | B2: E009 | C2: Payroll Officer | D2: E003 | E2: Agency | F2: 15 | G2: 2 | H2: Applied | I2: Score: 85% | J2: Subiaco Office | K2: WA | L2: Australia
A3: V002 | B3: E016 | C3: Sales Rep | D3: E007 | E3: Referral | F3: 21 | G3: 3 | H3: Interviewed | I3: Score: 85% | J3: Subiaco Office | K3: WA | L3: Australia
A4: V003 | B4: E004 | C4: Operations Staff | D4: E016 | E4: Job Board | F4: 23 | G4: 2 | H4: Interviewed | I4: Score: 85% | J4: Subiaco Office | K4: WA | L4: Australia
A5: V004 | B5: E006 | C5: Sales Rep | D5: E007 | E5: Agency | F5: 58 | G5: 3 | H5: Interviewed | I5: Score: 85% | J5: Subiaco Office | K5: WA | L5: Australia
A6: V005 | B6: E009 | C6: Operations Staff | D6: E016 | E6: Agency | F6: 24 | G6: 1 | H6: Hired | I6: Score: 85% | J6: Subiaco Office | K6: WA | L6: Australia

Sheet Advanced Analytics
A1: Employee ID | B1: Cost-to-Company | C1: Training Investment | D1: Productivity Index | E1: Attrition Probability | F1: Flight Risk Score | G1: Engagement Trend | H1: Promotion Velocity | I1: Critical Role Indicator
A2: E001 | B2: 105699 | C2: 1408 | D2: 118 | E2: 10% | F2: High | G2: Declining | H2: 5 | I2: Yes
A3: E002 | B3: 124603 | C3: 4378 | D3: 84 | E3: 14% | F3: Low | G3: Stable | H3: 3 | I3: Yes
A4: E003 | B4: 84572 | C4: 2336 | D4: 74 | E4: 25% | F4: High | G4: Declining | H4: 2 | I4: No
A5: E004 | B5: 186376 | C5: 3221 | D5: 117 | E5: 11% | F5: High | G5: Declining | H5: 1 | I5: No
A6: E005 | B6: 117409 | C6: 4103 | D6: 71 | E6: 22% | F6: High | G6: Improving | H6: 1 | I6: No
A7: E006 | B7: 86245 | C7: 3574 | D7: 104 | E7: 27% | F7: High | G7: Stable | H7: 2 | I7: Yes
A8: E007 | B8: 72341 | C8: 1536 | D8: 97 | E8: 22% | F8: Low | G8: Improving | H8: 5 | I8: Yes
A9: E008 | B9: 171838 | C9: 1595 | D9: 112 | E9: 30% | F9: Medium | G9: Stable | H9: 1 | I9: Yes
A10: E009 | B10: 171808 | C10: 4098 | D10: 103 | E10: 9% | F10: High | G10: Improving | H10: 3 | I10: Yes
A11: E010 | B11: 146780 | C11: 3939 | D11: 118 | E11: 13% | F11: Medium | G11: Declining | H11: 2 | I11: No
A12: E011 | B12: 106362 | C12: 1758 | D12: 102 | E12: 27% | F12: Low | G12: Improving | H12: 4 | I12: No
A13: E012 | B13: 179282 | C13: 4360 | D13: 97 | E13: 13% | F13: Medium | G13: Stable | H13: 5 | I13: No
... A21: E020 | B21: 103456 | C21: 570 | D21: 86 | E21: 17% | F21: High | G21: Declining | H21: 5 | I21: No

Sheet External Factors
A1: Date | B1: CPI | C1: Unemployment Rate | D1: Industry Turnover Rate | E1: Market Salary Benchmark | F1: Economic Confidence Index | G1: Job Vacancy Index
A2: 44927 | B2: 3.35 | C2: 3.86 | D2: 19 | E2: 79676 | F2: 81.93 | G2: 1329
A3: 44958 | B3: 2.8 | C3: 5.52 | D3: 11.75 | E3: 113612 | F3: 113.93 | G3: 2045
A4: 44986 | B4: 4.28 | C4: 5.32 | D4: 17.67 | E4: 100195 | F4: 106.59 | G4: 3093
A5: 45017 | B5: 3.97 | C5: 4.16 | D5: 14.69 | E5: 96703 | F5: 117.27 | G5: 3047
A6: 45047 | B6: 3.71 | C6: 3.77 | D6: 10 | E6: 108864 | F6: 100.17 | G6: 1566
A7: 45078 | B7: 2.94 | C7: 4.47 | D7: 19.82 | E7: 72341 | F7: 86.42 | G7: 3602
A8: 45108 | B8: 3.63 | C8: 3.82 | D8: 11.22 | E8: 87018 | F8: 80.84 | G8: 2512
A9: 45139 | B9: 4.85 | C9: 4.71 | D9: 11.77 | E9: 108041 | F9: 86.05 | G9: 3742
A10: 45170 | B10: 2.69 | C10: 4.29 | D10: 13.97 | E10: 80188 | F10: 100.89 | G10: 4773
A11: 45200 | B11: 4.88 | C11: 3.25 | D11: 14.79 | E11: 115275 | F11: 98.06 | G11: 1746
A12: 45231 | B12: 3.33 | C12: 4.85 | D12: 19.93 | E12: 79136 | F12: 86.24 | G12: 1589
A13: 45261 | B13: 4.78 | C13: 5.81 | D13: 18.94 | E13: 81865 | F13: 85.84 | G13: 2163
